MANIFEST.in
NEWS.txt
README.txt
TODO.txt
setup.py
bin/smewg
packaging/linux/falafelton-smewt.desktop
smewt/__init__.py
smewt.egg-info/PKG-INFO
smewt.egg-info/SOURCES.txt
smewt.egg-info/dependency_links.txt
smewt.egg-info/requires.txt
smewt.egg-info/top_level.txt
smewt/3rdparty/__init__.py
smewt/3rdparty/periscope/__init__.py
smewt/3rdparty/periscope/periscope.py
smewt/3rdparty/periscope/version.py
smewt/3rdparty/periscope/plugins/Addic7ed.py
smewt/3rdparty/periscope/plugins/BierDopje.py
smewt/3rdparty/periscope/plugins/OpenSubtitles.py
smewt/3rdparty/periscope/plugins/Podnapisi.py
smewt/3rdparty/periscope/plugins/SubtitleDatabase.py
smewt/3rdparty/periscope/plugins/Subtitulos.py
smewt/3rdparty/periscope/plugins/TheSubDB.py
smewt/3rdparty/periscope/plugins/TvSubtitles.py
smewt/3rdparty/periscope/plugins/__init__.py
smewt/base/__init__.py
smewt/base/actionfactory.py
smewt/base/cache.py
smewt/base/collection.py
smewt/base/eventserver.py
smewt/base/graphaction.py
smewt/base/importtask.py
smewt/base/mediaobject.py
smewt/base/singleapplication.py
smewt/base/smewtdaemon.py
smewt/base/smewtexception.py
smewt/base/smewturl.py
smewt/base/solvingchain.py
smewt/base/subtitletask.py
smewt/base/taskmanager.py
smewt/base/textutils.py
smewt/base/utils.py
smewt/guessers/__init__.py
smewt/guessers/episodefilename.py
smewt/guessers/episodetvdb.py
smewt/guessers/guesser.py
smewt/guessers/moviefilename.py
smewt/guessers/movietmdb.py
smewt/guessers/thetvdbapi.py
smewt/guessers/tmdb.py
smewt/guessers/tvdbmetadataprovider.py
smewt/gui/__init__.py
smewt/gui/aboutdialog.py
smewt/gui/collectionfolderspage.py
smewt/gui/dirselector.py
smewt/gui/feedwatchwidget.py
smewt/gui/mainwidget.py
smewt/icons/__init__.py
smewt/icons/falafelton-smewt_128x128.png
smewt/icons/go-home.png
smewt/icons/go-next.png
smewt/icons/go-previous.png
smewt/icons/smewt.svg
smewt/icons/smewt_64x64.png
smewt/icons/view-fullscreen.png
smewt/icons/view-refresh.png
smewt/icons/zoom-in.png
smewt/icons/zoom-out.png
smewt/media/__init__.py
smewt/media/3rdparty/__init__.py
smewt/media/3rdparty/styler.js
smewt/media/3rdparty/tabber.js
