Metadata-Version: 1.0
Name: smewt
Version: 0.3.1
Summary: Smewt - a smart media manager.
Home-page: http://www.smewt.com/
Author: Nicolas Wack, Ricard Marxer
Author-email: wackou@gmail.com
License: GPLv3
Keywords: smewt pygoo media manager video collection
Platform: UNKNOWN
